README.md
setup.py
merge_json/__init__.py
merge_json/merger.py
merge_json/splitter.py
merge_json.egg-info/PKG-INFO
merge_json.egg-info/SOURCES.txt
merge_json.egg-info/dependency_links.txt
merge_json.egg-info/top_level.txt
merge_json.egg-info/zip-safe