Metadata-Version: 1.0
Name: merge-json
Version: 0.1.0
Summary: Mhmhmhmhmh, merge jsons
Home-page: https://github.com/messier16/merge_json
Author: Antonio Feregrino
Author-email: antonio.feregrino@messier16.com
License: MIT
Platform: UNKNOWN
